Metadata-Version: 2.1
Name: crImageProcessing
Version: 0.0.1
Summary: Image Processing Package using scikit-image
Home-page: https://github.com/tyssondocarmo/image-processing-package.git
Author: tyssondocarmo
Author-email: tyssoncr@gmail.com
Requires-Python: >=3.8
Requires-Dist: matplotlib
Requires-Dist: numpy
Requires-Dist: scikit-image
